Workbook
Name NetIncome: 'Profit and Loss'!$O$9

Sheet Profit and Loss
B1: {YEAR} | C1: PROFIT AND LOSS STATEMENT | L1: NET INCOME
C2: {COMPANY NAME} | L2: =NetIncome -> 150617.84
B3: Line chart showing Gross Profit and Total Operation Expenses is in this cell. Enter data in table below.
C4: JAN | D4: FEB | E4: MAR | F4: APR | G4: MAY | H4: JUN | I4: JUL | J4: AUG | K4: SEP | L4: OCT | M4: NOV | N4: DEC | O4: YTD
B5: Income From Operations | C5: =IFERROR(Revenue!C11-'Operation Expenses'!$C$17,"") -> 13750 | D5: =IFERROR(Revenue!D11-'Operation Expenses'!$D$17,"") -> 12927.5 | E5: =IFERROR(Revenue!E11-'Operation Expenses'!$E$17,"") -> 13114.62 | F5: =IFERROR(Revenue!F11-'Operation Expenses'!$F$17,"") -> 12787.25 | G5: =IFERROR(Revenue!G11-'Operation Expenses'!$G$17,"") -> 12208.27 | H5: =IFERROR(Revenue!H11-'Operation Expenses'!$H$17,"") -> 13207.6 | I5: =IFERROR(Revenue!I11-'Operation Expenses'!$I$17,"") -> 11842.45 | J5: =IFERROR(Revenue!J11-'Operation Expenses'!$J$17,"") -> 19819.32 | K5: =IFERROR(Revenue!K11-'Operation Expenses'!$K$17,"") -> 18495.04 | L5: =IFERROR(Revenue!L11-'Operation Expenses'!$L$17,"") -> 11469.54 | M5: =IFERROR(Revenue!M11-'Operation Expenses'!$M$17,"") -> 18442.78 | N5: =IFERROR(Revenue!N11-'Operation Expenses'!$N$17,"") -> 12667.67 | O5: =IFERROR(Revenue!O11-'Operation Expenses'!$O$17,"") -> 170732.04
B6: Interest Income (Expense) | C6: -100 | D6: -105 | E6: -110.25 | F6: -115.76 | G6: -121.55 | H6: -127.63 | I6: -134.01 | O6: =SUM(C6:N6) -> -814.2
B7: Income Before Income Taxes | C7: =IFERROR(C5+C6,"") -> 13650 | D7: =IFERROR(D5+D6,"") -> 12822.5 | E7: =IFERROR(E5+E6,"") -> 13004.37 | F7: =IFERROR(F5+F6,"") -> 12671.49 | G7: =IFERROR(G5+G6,"") -> 12086.72 | H7: =IFERROR(H5+H6,"") -> 13079.97 | I7: =IFERROR(I5+I6,"") -> 11708.44 | J7: =IFERROR(J5+J6,"") -> 19819.32 | ... N7: =IFERROR(N5+N6,"") -> 12667.67 | O7: =SUM(C7:N7) -> 169917.84
B8: Income Tax Expense | C8: 2400 | D8: 2500 | E8: 2600 | F8: 2700 | G8: 2900 | H8: 3000 | I8: 3200 | O8: =SUM(C8:N8) -> 19300
B9: Net Income | C9: =IFERROR(C7-C8,"") -> 11250 | D9: =IFERROR(D7-D8,"") -> 10322.5 | E9: =IFERROR(E7-E8,"") -> 10404.37 | F9: =IFERROR(F7-F8,"") -> 9971.49 | G9: =IFERROR(G7-G8,"") -> 9186.72 | H9: =IFERROR(H7-H8,"") -> 10079.97 | I9: =IFERROR(I7-I8,"") -> 8508.44 | J9: =IFERROR(J7-J8,"") -> 19819.32 | ... O9: =IFERROR(O7-O8,"") -> 150617.84

Sheet Revenue
B1: ='Operation Expenses'!B1:B2 -> {YEAR} | C1: PROFIT AND LOSS STATEMENT - REVENUE
C2: ='Profit and Loss'!C2:K2 -> {COMPANY NAME}
B3: Revenue | C3: JAN | D3: FEB | E3: MAR | F3: APR | G3: MAY | H3: JUN | I3: JUL | J3: AUG | K3: SEP | L3: OCT | M3: NOV | N3: DEC | O3: YTD
B4: Sales | C4: 25000 | D4: 25000 | E4: 25000 | F4: 25000 | G4: 25000 | H4: 25000 | I4: 25000 | J4: 25000 | K4: 25000 | L4: 25000 | M4: 25000 | N4: 25000 | O4: =SUM(C4:N4) -> 300000
B5: Sales Returns (Reduction) | C5: 0 | D5: -500 | E5: 0 | F5: 0 | G5: -234 | H5: 0 | I5: 0 | J5: -300 | K5: 0 | L5: -300 | M5: 0 | N5: -234 | O5: =SUM(C5:N5) -> -1568
B6: Sales Discounts (Reduction) | C6: -5000 | D6: -5250 | E6: -5513 | F6: -5788 | G6: -6078 | H6: -5324 | I6: -6700 | J6: -400 | K6: 0 | L6: -6700 | M6: 0 | N6: -5513 | O6: =SUM(C6:N6) -> -52266
B7: Other Revenue 1 | C7: 0 | D7: 0 | E7: 0 | F7: 0 | G7: 0 | H7: 0 | I7: 0 | J7: 2000 | K7: 0 | L7: 0 | M7: 0 | N7: 0 | O7: =SUM(C7:N7) -> 2000
B8: Other Revenue 2 | C8: 0 | D8: 0 | E8: 0 | F8: 0 | G8: 0 | H8: 0 | I8: 0 | J8: 0 | K8: 0 | L8: 0 | M8: 0 | N8: 0 | O8: =SUM(C8:N8) -> 0
B9: Other Revenue 3 | C9: 0 | D9: 0 | E9: 0 | F9: 0 | G9: 0 | H9: 0 | I9: 0 | J9: 0 | K9: 0 | L9: 0 | M9: 0 | N9: 0 | O9: =SUM(C9:N9) -> 0
B10: Net Sales | C10: =IF(SUM(C3:C8)=0,"",SUM(C3:C8)) -> 20000 | D10: =IF(SUM(D3:D8)=0,"",SUM(D3:D8)) -> 19250 | E10: =IF(SUM(E3:E8)=0,"",SUM(E3:E8)) -> 19487 | F10: =IF(SUM(F3:F8)=0,"",SUM(F3:F8)) -> 19212 | G10: =IF(SUM(G3:G8)=0,"",SUM(G3:G8)) -> 18688 | H10: =IF(SUM(H3:H8)=0,"",SUM(H3:H8)) -> 19676 | I10: =IF(SUM(I3:I8)=0,"",SUM(I3:I8)) -> 18300 | J10: =IF(SUM(J3:J8)=0,"",SUM(J3:J8)) -> 26300 | ... N10: =IF(SUM(N3:N8)=0,"",SUM(N3:N8)) -> 19253 | O10: =SUBTOTAL(109,Revenue!$O$4:$O$9) -> 248166
B11: Gross Profit | C11: =C10 -> 20000 | D11: =D10 -> 19250 | E11: =E10 -> 19487 | F11: =F10 -> 19212 | G11: =G10 -> 18688 | H11: =H10 -> 19676 | I11: =I10 -> 18300 | J11: =J10 -> 26300 | ... O11: =O10 -> 248166

Sheet Operation Expenses
B1: ='Profit and Loss'!B1:B2 -> {YEAR} | C1: PROFIT AND LOSS STATEMENT - OPERATION EXPENSES
C2: ='Profit and Loss'!C2:K2 -> {COMPANY NAME}
B3: Operation Expenses | C3: JAN | D3: FEB | E3: MAR | F3: APR | G3: MAY | H3: JUN | I3: JUL | J3: AUG | K3: SEP | L3: OCT | M3: NOV | N3: DEC | O3: YTD
B4: Salaries & Wages | C4: 5000 | D4: 5000 | E4: 5000 | F4: 5000 | G4: 5000 | H4: 5000 | I4: 5000 | J4: 5000 | K4: 5000 | L4: 5000 | M4: 5000 | N4: 5000 | O4: =SUM(C4:N4) -> 60000
B5: Depreciation | C5: 500 | D5: 525 | E5: 551.25 | F5: 578.81 | G5: 607.75 | H5: 638.14 | I5: 670.05 | J5: 670.05 | K5: 670.05 | L5: 670.05 | M5: 670.05 | N5: 670.05 | O5: =SUM(C5:N5) -> 7421.25
B6: Rent | C6: 0 | D6: 0 | E6: 0 | F6: 0 | G6: 0 | H6: 0 | I6: 0 | J6: 0 | K6: 0 | L6: 0 | M6: 0 | N6: 0 | O6: =SUM(C6:N6) -> 0
B7: Office Supplies | C7: 100 | D7: 100 | E7: 100 | F7: 100 | G7: 100 | H7: 100 | I7: 100 | J7: 100 | K7: 100 | L7: 100 | M7: 100 | N7: 100 | O7: =SUM(C7:N7) -> 1200
B8: Utilities | C8: 0 | D8: 0 | E8: 0 | F8: 0 | G8: 0 | H8: 0 | I8: 0 | J8: 0 | K8: 0 | L8: 0 | M8: 0 | N8: 0 | O8: =SUM(C8:N8) -> 0
B9: Telephone | C9: 100 | D9: 100 | E9: 100 | F9: 100 | G9: 100 | H9: 100 | I9: 100 | J9: 100 | K9: 100 | L9: 100 | M9: 100 | N9: 100 | O9: =SUM(C9:N9) -> 1200
B10: Insurance | C10: 100 | D10: 125 | E10: 125 | F10: 125 | G10: 125 | H10: 125 | I10: 125 | J10: 125 | K10: 125 | L10: 125 | M10: 125 | N10: 125 | O10: =SUM(C10:N10) -> 1475
B11: Travel | C11: 250 | D11: 262.5 | E11: 275.63 | F11: 289.41 | G11: 303.88 | H11: 250 | I11: 262.5 | J11: 275.63 | K11: 289.41 | L11: 303.88 | M11: 319.07 | N11: 335.02 | O11: =SUM(C11:N11) -> 3416.93
B12: Maintenance | C12: 0 | D12: 0 | E12: 0 | F12: 0 | G12: 0 | H12: 0 | I12: 0 | J12: 0 | K12: 0 | L12: 0 | M12: 0 | N12: 0 | O12: =SUM(C12:N12) -> 0
B13: Advertising | C13: 200 | D13: 210 | E13: 220.5 | F13: 231.53 | G13: 243.1 | H13: 255.26 | I13: 200 | J13: 210 | K13: 220.5 | L13: 231.53 | M13: 243.1 | N13: 255.26 | O13: =SUM(C13:N13) -> 2720.78
B14: Other 1 | C14: 0 | D14: 0 | E14: 0 | F14: 0 | G14: 0 | H14: 0 | I14: 0 | J14: 0 | K14: 0 | L14: 0 | M14: 0 | N14: 0 | O14: =SUM(C14:N14) -> 0
B15: Other 2 | C15: 0 | D15: 0 | E15: 0 | F15: 0 | G15: 0 | H15: 0 | I15: 0 | J15: 0 | K15: 0 | L15: 0 | M15: 0 | N15: 0 | O15: =SUM(C15:N15) -> 0
B16: Other 3 | C16: 0 | D16: 0 | E16: 0 | F16: 0 | G16: 0 | H16: 0 | I16: 0 | J16: 0 | K16: 0 | L16: 0 | M16: 0 | N16: 0 | O16: =SUM(C16:N16) -> 0
B17: Total Operation Expenses | C17: =IF(SUM(C4:C16)=0,"",SUM(C4:C16)) -> 6250 | D17: =IF(SUM(D4:D16)=0,"",SUM(D4:D16)) -> 6322.5 | E17: =IF(SUM(E4:E16)=0,"",SUM(E4:E16)) -> 6372.38 | F17: =IF(SUM(F4:F16)=0,"",SUM(F4:F16)) -> 6424.75 | G17: =IF(SUM(G4:G16)=0,"",SUM(G4:G16)) -> 6479.73 | H17: =IF(SUM(H4:H16)=0,"",SUM(H4:H16)) -> 6468.4 | I17: =IF(SUM(I4:I16)=0,"",SUM(I4:I16)) -> 6457.55 | J17: =IF(SUM(J4:J16)=0,"",SUM(J4:J16)) -> 6480.68 | ... N17: =IF(SUM(N4:N16)=0,"",SUM(N4:N16)) -> 6585.33 | O17: =SUBTOTAL(109,'Operation Expenses'!$O$4:$O$16) -> 77433.96
